.gitignore
.readthedocs.yml
AUTHORS.txt
CHANGELOG.rst
COPYING
COPYING.LESSER
MANIFEST.in
README.rst
pyproject.toml
setup.py
tox.ini
.github/workflows/publish-sdist.yml
.github/workflows/run-tox.yml
bluepysnap/__init__.py
bluepysnap/_doctools.py
bluepysnap/_plotting.py
bluepysnap/_version.py
bluepysnap/bbp.py
bluepysnap/circuit.py
bluepysnap/circuit_ids.py
bluepysnap/circuit_ids_types.py
bluepysnap/circuit_validation.py
bluepysnap/cli.py
bluepysnap/config.py
bluepysnap/exceptions.py
bluepysnap/frame_report.py
bluepysnap/input.py
bluepysnap/morph.py
bluepysnap/network.py
bluepysnap/neuron_models.py
bluepysnap/node_sets.py
bluepysnap/query.py
bluepysnap/settings.py
bluepysnap/simulation.py
bluepysnap/simulation_validation.py
bluepysnap/sonata_constants.py
bluepysnap/spike_report.py
bluepysnap/utils.py
bluepysnap.egg-info/PKG-INFO
bluepysnap.egg-info/SOURCES.txt
bluepysnap.egg-info/dependency_links.txt
bluepysnap.egg-info/entry_points.txt
bluepysnap.egg-info/requires.txt
bluepysnap.egg-info/top_level.txt
bluepysnap/edges/__init__.py
bluepysnap/edges/edge_population.py
bluepysnap/edges/edge_population_stats.py
bluepysnap/edges/edges.py
bluepysnap/nodes/__init__.py
bluepysnap/nodes/node_population.py
bluepysnap/nodes/nodes.py
bluepysnap/schemas/__init__.py
bluepysnap/schemas/circuit.yaml
bluepysnap/schemas/schemas.py
bluepysnap/schemas/simulation.yaml
bluepysnap/schemas/definitions/datatypes.yaml
bluepysnap/schemas/definitions/edge.yaml
bluepysnap/schemas/definitions/node.yaml
bluepysnap/schemas/definitions/simulation_input.yaml
bluepysnap/schemas/edge/chemical.yaml
bluepysnap/schemas/edge/chemical_virtual.yaml
bluepysnap/schemas/edge/electrical.yaml
bluepysnap/schemas/edge/endfoot.yaml
bluepysnap/schemas/edge/glialglial.yaml
bluepysnap/schemas/edge/neuromodulatory.yaml
bluepysnap/schemas/edge/synapse_astrocyte.yaml
bluepysnap/schemas/node/astrocyte.yaml
bluepysnap/schemas/node/biophysical.yaml
bluepysnap/schemas/node/vasculature.yaml
bluepysnap/schemas/node/virtual.yaml
doc/Makefile
doc/make.bat
doc/source/api.rst
doc/source/changelog.rst
doc/source/circuits.rst
doc/source/conf.py
doc/source/index.rst
doc/source/notebooks.rst
doc/source/simulations.rst
