Metadata-Version: 2.4
Name: bluepysnap
Version: 3.0.2
Summary: Simulation and Neural network Analysis Productivity layer
Home-page: https://github.com/BlueBrain/snap
Author: Blue Brain Project, EPFL
License: LGPLv3
Keywords: SONATA,BlueBrainProject
Classifier: Development Status :: 3 - Alpha
Classifier: Programming Language :: Python :: 3.8
Classifier: Programming Language :: Python :: 3.9
Classifier: Programming Language :: Python :: 3.10
Classifier: Programming Language :: Python :: 3.11
Classifier: Programming Language :: Python :: 3.12
Classifier: Programming Language :: Python :: 3.13
Classifier: Operating System :: POSIX
Classifier: Topic :: Scientific/Engineering
Classifier: Topic :: Utilities
Classifier: License :: OSI Approved :: GNU Lesser General Public License v3 (LGPLv3)
Requires-Python: >=3.8
License-File: COPYING
License-File: COPYING.LESSER
License-File: AUTHORS.txt
Requires-Dist: brain-indexer>=3.0.0
Requires-Dist: cached_property>=1.0
Requires-Dist: h5py<4.0.0,>=3.0.1
Requires-Dist: importlib_resources>=5.0.0
Requires-Dist: jsonschema<5.0.0,>=4.0.0
Requires-Dist: libsonata<1.0.0,>=0.1.24
Requires-Dist: morphio<4.0.0,>=3.3.5
Requires-Dist: morph-tool<3.0.0,>=2.4.3
Requires-Dist: numpy>=1.8
Requires-Dist: pandas>=1.0.0
Requires-Dist: click>=7.0
Requires-Dist: more-itertools>=8.2.0
Provides-Extra: docs
Requires-Dist: sphinx; extra == "docs"
Requires-Dist: sphinx-bluebrain-theme; extra == "docs"
Provides-Extra: plots
Requires-Dist: matplotlib>=3.0.0; extra == "plots"
Dynamic: author
Dynamic: classifier
Dynamic: description
Dynamic: description-content-type
Dynamic: home-page
Dynamic: keywords
Dynamic: license
Dynamic: license-file
Dynamic: provides-extra
Dynamic: requires-dist
Dynamic: requires-python
Dynamic: summary
